parcomb/__init__.py
parcomb/char.py
parcomb/combinator.py
parcomb/common.py
parcomb/number.py
parcomb/parsing.py
parcomb/py.typed
parcomb/regex.py
parcomb/response.py
parcomb/string.py
parcomb-0.13.0.dist-info/LICENSE
parcomb-0.13.0.dist-info/WHEEL
parcomb-0.13.0.dist-info/METADATA
parcomb-0.13.0.dist-info/RECORD
